midas_bdk-0.0.5.data/scripts/midasbuild
midas_bdk-0.0.5.data/scripts/midascreate
midas_bdk-0.0.5.dist-info/DESCRIPTION.rst
midas_bdk-0.0.5.dist-info/METADATA
midas_bdk-0.0.5.dist-info/RECORD
midas_bdk-0.0.5.dist-info/WHEEL
midas_bdk-0.0.5.dist-info/metadata.json
midas_bdk-0.0.5.dist-info/top_level.txt
midasbdk/__init__.py
midasbdk/run_sim.py
midasbdk/brains/__init__.py
midasbdk/brains/brain.py
midasbdk/data/__init__.py
midasbdk/data/dataloader.py
midasbdk/data/example.json
midasbdk/data/hyundaimotors.json
midasbdk/data/lgchemical.json
midasbdk/data/samsungelectronics.json
midasbdk/midas/__init__.py
midasbdk/midas/trader.py
midasbdk/midas/Stock/Trader.py
midasbdk/midas/Stock/VDaishinTrader.py
midasbdk/midas/Stock/__init__.py
midasbdk/midas/Stock/util.py
midasbdk/simulator/__init__.py
midasbdk/simulator/sim.py
midasbdk/utils/__init__.py
midasbdk/utils/average.py
