Metadata-Version: 2.0
Name: midas-bdk
Version: 0.0.5
Summary: midas BDK
Home-page: UNKNOWN
Author: hyeonjae
Author-email: bakhyeonjae@gmail.com
License: UNKNOWN
Keywords: midas
Platform: UNKNOWN
Classifier: Programming Language :: Python :: 3
Classifier: Programming Language :: Python :: 3.2
Classifier: Programming Language :: Python :: 3.3
Classifier: Programming Language :: Python :: 3.4
Classifier: Programming Language :: Python :: 3.5
Classifier: Programming Language :: Python :: 3.6
Classifier: Programming Language :: Python :: 3.7
